open_hypergraphs/__init__.py
open_hypergraphs/finite_function.py
open_hypergraphs/hypergraph.py
open_hypergraphs/open_hypergraph.py
open_hypergraphs/py.typed
open_hypergraphs/array/__init__.py
open_hypergraphs/array/backend.py
open_hypergraphs/array/numpy.py
open_hypergraphs/functor/__init__.py
open_hypergraphs/functor/functor.py
open_hypergraphs/functor/optic.py
open_hypergraphs/numpy/__init__.py
open_hypergraphs/numpy/layer.py
open_hypergraphs/numpy/types.py
open_hypergraphs-0.1.3.dist-info/METADATA
open_hypergraphs-0.1.3.dist-info/WHEEL
open_hypergraphs-0.1.3.dist-info/licenses/LICENSE
open_hypergraphs-0.1.3.dist-info/RECORD
